enet.cp311-win_amd64.pyd
pyenet311-1.3.14.dist-info/LICENSE
pyenet311-1.3.14.dist-info/METADATA
pyenet311-1.3.14.dist-info/WHEEL
pyenet311-1.3.14.dist-info/top_level.txt
pyenet311-1.3.14.dist-info/RECORD
